LICENSE.txt
MANIFEST.in
README.rst
release-history.rst
requirements.txt
setup.py
wechinelearn/__init__.py
wechinelearn/config.py
wechinelearn/database.py
wechinelearn/munging.py
wechinelearn/selector.py
wechinelearn/zzz_manual_install.py
wechinelearn.egg-info/PKG-INFO
wechinelearn.egg-info/SOURCES.txt
wechinelearn.egg-info/dependency_links.txt
wechinelearn.egg-info/requires.txt
wechinelearn.egg-info/top_level.txt
wechinelearn/__pycache__/__init__.cpython-33.pyc